streamlit_text_rating/__init__.py
streamlit_text_rating/st_text_rater.py
streamlit_text_rating/version.py
streamlit_text_rating/frontend/build/asset-manifest.json
streamlit_text_rating/frontend/build/bootstrap.min.css
streamlit_text_rating/frontend/build/dislike.png
streamlit_text_rating/frontend/build/index.html
streamlit_text_rating/frontend/build/like-button.png
streamlit_text_rating/frontend/build/precache-manifest.ff264b8d2a0ca9129428fd2dd8c04594.js
streamlit_text_rating/frontend/build/service-worker.js
streamlit_text_rating/frontend/build/thumbsup.svg
streamlit_text_rating/frontend/build/static/js/2.a69c7c9c.chunk.js
streamlit_text_rating/frontend/build/static/js/2.a69c7c9c.chunk.js.LICENSE.txt
streamlit_text_rating/frontend/build/static/js/2.a69c7c9c.chunk.js.map
streamlit_text_rating/frontend/build/static/js/main.765c33cd.chunk.js
streamlit_text_rating/frontend/build/static/js/main.765c33cd.chunk.js.map
streamlit_text_rating/frontend/build/static/js/runtime-main.11ec9aca.js
streamlit_text_rating/frontend/build/static/js/runtime-main.11ec9aca.js.map
streamlit_text_rating_component-0.1.9.dist-info/METADATA
streamlit_text_rating_component-0.1.9.dist-info/WHEEL
streamlit_text_rating_component-0.1.9.dist-info/top_level.txt
streamlit_text_rating_component-0.1.9.dist-info/RECORD
